verilator/__init__.py
verilator/__main__.py
verilator/verilator-config-version.cmake
verilator/verilator-config.cmake
verilator/bin/verilator
verilator/bin/verilator_bin
verilator/bin/verilator_ccache_report
verilator/bin/verilator_difftree
verilator/bin/verilator_gantt
verilator/bin/verilator_includer
verilator/bin/verilator_profcfunc
verilator/examples/cmake_hello_c/CMakeLists.txt
verilator/examples/cmake_hello_c/Makefile
verilator/examples/cmake_hello_sc/CMakeLists.txt
verilator/examples/cmake_hello_sc/Makefile
verilator/examples/cmake_protect_lib/CMakeLists.txt
verilator/examples/cmake_protect_lib/Makefile
verilator/examples/cmake_tracing_c/CMakeLists.txt
verilator/examples/cmake_tracing_c/Makefile
verilator/examples/cmake_tracing_sc/CMakeLists.txt
verilator/examples/cmake_tracing_sc/Makefile
verilator/examples/json_py/Makefile
verilator/examples/json_py/sub.v
verilator/examples/json_py/top.v
verilator/examples/make_hello_binary/Makefile
verilator/examples/make_hello_binary/top.v
verilator/examples/make_hello_c/Makefile
verilator/examples/make_hello_c/sim_main.cpp
verilator/examples/make_hello_c/top.v
verilator/examples/make_hello_sc/Makefile
verilator/examples/make_hello_sc/sc_main.cpp
verilator/examples/make_hello_sc/top.v
verilator/examples/make_protect_lib/Makefile
verilator/examples/make_protect_lib/secret_impl.v
verilator/examples/make_protect_lib/sim_main.cpp
verilator/examples/make_protect_lib/top.v
verilator/examples/make_tracing_c/Makefile
verilator/examples/make_tracing_c/Makefile_obj
verilator/examples/make_tracing_c/input.vc
verilator/examples/make_tracing_c/sim_main.cpp
verilator/examples/make_tracing_c/sub.v
verilator/examples/make_tracing_c/top.v
verilator/examples/make_tracing_sc/Makefile
verilator/examples/make_tracing_sc/Makefile_obj
verilator/examples/make_tracing_sc/input.vc
verilator/examples/make_tracing_sc/sc_main.cpp
verilator/examples/make_tracing_sc/sub.v
verilator_dspsim-5.42.3.dist-info/METADATA
verilator_dspsim-5.42.3.dist-info/WHEEL
verilator_dspsim-5.42.3.dist-info/entry_points.txt
verilator_dspsim-5.42.3.dist-info/RECORD
verilator_dspsim-5.42.3.dist-info/licenses/LICENSE
