Metadata-Version: 2.2
Name: verilator-dspsim
Version: 5.42.3
Summary: A Python wrapper around an installation of Verilator.
Author: Frank Sodari
Classifier: Intended Audience :: Developers
Classifier: License :: OSI Approved :: GNU Lesser General Public License v3 (LGPLv3)
Classifier: Programming Language :: C++
Classifier: Programming Language :: Python :: 3 :: Only
Classifier: Programming Language :: Python :: Implementation :: CPython
Classifier: Topic :: Software Development :: Libraries :: Python Modules
Classifier: Topic :: Utilities
Project-URL: Homepage, https://github.com/fsodari/verilator-python
